profit_potion/__init__.py
profit_potion/magic/__init__.py
profit_potion/magic/index.py
profit_potion-0.1.0.dist-info/METADATA
profit_potion-0.1.0.dist-info/WHEEL
profit_potion-0.1.0.dist-info/top_level.txt
profit_potion-0.1.0.dist-info/RECORD
