Metadata-Version: 2.1
Name: profit-potion
Version: 0.1.0
Summary: A magical financial analysis library.
Home-page: https://gitlab.com/gabwill10/profit-potion.git
Author: Gabriel Gonzalez
Author-email: gabrielgonzalezcifuentes@gmail.com
Classifier: Programming Language :: Python :: 3
Classifier: License :: OSI Approved :: MIT License
Classifier: Operating System :: OS Independent
Requires-Python: >=3.8
Requires-Dist: requests >=2.32.3
Requires-Dist: openai >=1.35.3
